iclientpy/__init__.py
iclientpy/_version.py
iclientpy/dtojson/__init__.py
iclientpy/jupyter/__init__.py
iclientpy/jupyter/chinageojson.json
iclientpy/jupyter/units.py
iclientpy/jupyter/widgets/__init__.py
iclientpy/jupyter/widgets/basesetting.py
iclientpy/jupyter/widgets/cloudtilelayer.py
iclientpy/jupyter/widgets/heatlayer.py
iclientpy/jupyter/widgets/mapview.py
iclientpy/jupyter/widgets/mapvlayer.py
iclientpy/jupyter/widgets/ranksymbolthemelayer.py
iclientpy/jupyter/widgets/tilemaplayer.py
iclientpy/rest/__init__.py
iclientpy/rest/apifactory.py
iclientpy/rest/decorator.py
iclientpy/rest/proxyfactory.py
iclientpy/rest/api/__init__.py
iclientpy/rest/api/management.py
iclientpy/rest/api/model.py
iclientpy/rest/api/restdata.py
iclientpy/static/extension.js
iclientpy/static/index.js
iclientpy/static/index.js.map
iclientpy/static/lib.js
iclientpy-9.0.0.1.data/data/share/jupyter/nbextensions/iclientpy/chinageojson.json
iclientpy-9.0.0.1.data/data/share/jupyter/nbextensions/iclientpy/extension.js
iclientpy-9.0.0.1.data/data/share/jupyter/nbextensions/iclientpy/index.js
iclientpy-9.0.0.1.data/data/share/jupyter/nbextensions/iclientpy/index.js.map
iclientpy-9.0.0.1.data/data/share/jupyter/nbextensions/iclientpy/lib.js
iclientpy-9.0.0.1.dist-info/DESCRIPTION.rst
iclientpy-9.0.0.1.dist-info/METADATA
iclientpy-9.0.0.1.dist-info/RECORD
iclientpy-9.0.0.1.dist-info/WHEEL
iclientpy-9.0.0.1.dist-info/metadata.json
iclientpy-9.0.0.1.dist-info/top_level.txt
test/dtojson/__init__.py
test/dtojson/test_dtojson.py
test/jupyter/__init__.py
test/jupyter/debug.py
test/jupyter/test_units.py
test/jupyter/widgets/__init__.py
test/jupyter/widgets/test_basesettings.py
test/jupyter/widgets/test_cloudtilelayer.py
test/jupyter/widgets/test_heatlayer.py
test/jupyter/widgets/test_mapview.py
test/jupyter/widgets/test_mapvlayer.py
test/jupyter/widgets/test_ranksymbolthemelayer.py
test/jupyter/widgets/test_tilemaplayer.py
test/rest/__init__.py
test/rest/test_REST.py
test/rest/test_api.py
test/rest/test_proxyfactory.py
test/rest/api/__init__.py
test/rest/api/abstractrest.py
test/rest/api/test_management.py
test/rest/api/test_restdata.py
