Metadata-Version: 2.0
Name: iclientpy
Version: 9.0.0.1
Summary: iclient for jupyter
Home-page: https://gitee.com/isupermap/iClientPython
Author: supermap
Author-email: supermap@supermap.com
License: UNKNOWN
Keywords: ipython,jupyter,widgets
Platform: UNKNOWN
Classifier: Development Status :: 4 - Beta
Classifier: Framework :: IPython
Classifier: Intended Audience :: Developers
Classifier: Intended Audience :: Science/Research
Classifier: Topic :: Multimedia :: Graphics
Classifier: Programming Language :: Python :: 2
Classifier: Programming Language :: Python :: 2.7
Classifier: Programming Language :: Python :: 3
Classifier: Programming Language :: Python :: 3.3
Classifier: Programming Language :: Python :: 3.4
Classifier: Programming Language :: Python :: 3.5
Requires-Dist: geojson (>=2.3.0)
Requires-Dist: ipyleaflet (>=0.5.1)
Requires-Dist: ipywidgets (>=7.0.0)
Requires-Dist: pandas (>=0.20.3)
